{
  "ItemId": 60001625,
  "MonsterId": 6000162,
  "ParentMonsterId": 0,
  "MonsterName": "夢魘·青羽鷺",
  "ElementType": [
    5
  ],
  "MainProp": {
    "RandGroupId": 502,
    "RandNum": 1
  },
  "LevelUpGroupId": 4,
  "SkillId": 200018,
  "CalabashBuffs": [
    70046
  ],
  "Rarity": 1,
  "MeshId": 200100,
  "Zoom": [
    0.800000011920929,
    0.800000011920929,
    0.800000011920929
  ],
  "Location": [
    0,
    0,
    0
  ],
  "Rotator": [
    0,
    0,
    15
  ],
  "StandAnim": "/Game/Aki/Character/Monster/Elite/ME1JingNiaoMd00401/CommonAnim/Stand2_yingzi.Stand2_yingzi",
  "TypeDescription": "聲骸",
  "AttributesDescription": "裝備後可以獲得屬性、主動技能和特定效果加成。",
  "Icon": "https://api-v2.encore.moe/resource/Data/Game/Aki/UI/UIResources/Common/Image/IconMonsterHead/T_IconMonsterHead_32046_UI.png",
  "IconMiddle": "https://api-v2.encore.moe/resource/Data/Game/Aki/UI/UIResources/Common/Image/IconMonsterGoods160/T_IconMonsterGoods160_32046_UI.png",
  "IconSmall": "https://api-v2.encore.moe/resource/Data/Game/Aki/UI/UIResources/Common/Image/IconMonsterGoods80/T_IconMonsterGoods80_32046_UI.png",
  "Mesh": "/Game/Aki/Scene/Assets/Common/Interaction/Mesh/SM_Pro_Roc_04ES.SM_Pro_Roc_04ES",
  "QualityId": 5,
  "MaxCapcity": 999999999,
  "ItemAccess": [],
  "ObtainedShow": 1,
  "ObtainedShowDescription": "解鎖聲骸。",
  "NumLimit": 0,
  "ShowInBag": true,
  "SortIndex": 0,
  "SkillIcon": "",
  "Destructible": true,
  "RedDotDisableRule": 0,
  "FetterGroup": [
    21
  ],
  "PhantomType": 1,
  "Skill": {
    "Id": 42,
    "PhantomSkillId": 200018,
    "BuffIds": [],
    "SettleIds": [
      20001801
    ],
    "BuffEffects": [],
    "ChargeEfficiency": 0,
    "SkillGroupId": 200001,
    "SkillCD": 15,
    "DescriptionEx": "使用聲骸技能，幻形為青羽鷺，攜卷旋風進行衝鋒，造成236.80%氣動傷害；對施放<color=Highlight>特殊技</color>的敵人造成傷害時能夠擊破對方的<color=Highlight>特殊技</color>。<br>技能冷卻：15秒",
    "SimplyDescription": "幻形為青羽鷺發動旋轉衝鋒，造成氣動傷害，擊破敵人的<color=Highlight>特殊技</color>。",
    "IfCounterSkill": true,
    "CurLevelDescriptionEx": [
      "49",
      "3",
      "11",
      "13"
    ],
    "LevelDescStrArray": [
      {
        "ArrayString": [
          "148.00%",
          "15"
        ]
      },
      {
        "ArrayString": [
          "170.20%",
          "15"
        ]
      },
      {
        "ArrayString": [
          "192.40%",
          "15"
        ]
      },
      {
        "ArrayString": [
          "214.60%",
          "15"
        ]
      },
      {
        "ArrayString": [
          "236.80%",
          "15"
        ]
      }
    ],
    "BattleViewIcon": "https://api-v2.encore.moe/resource/Data/Game/Aki/UI/UIResources/Common/Image/MstSkill/T_MstSkil_Z_B1_UI.png",
    "SpecialBattleViewIcon": "/Game/Aki/UI/UIResources/Common/Image/MstSkill/T_MstSkil_Z_B1_UI.T_MstSkil_Z_B1_UI",
    "SpecialViewIcon": ""
  },
  "ElementIcon": "https://api-v2.encore.moe/resource/Data/Game/Aki/UI/UIResources/Common/Image/IconElementRound/T_IconElementLight1_UI.png",
  "Element": {
    "Id": 5,
    "Name": "衍射",
    "Icon": "https://api-v2.encore.moe/resource/Data/Game/Aki/UI/UIResources/Common/Image/IconElementRound/T_IconElementLight1_UI.png"
  },
  "FetterGroupDetails": [
    {
      "Group": {
        "Id": 21,
        "FetterMap": [
          {
            "Key": 3,
            "Value": 213
          }
        ],
        "FetterType": 1,
        "FetterGroupName": "息界同調之律",
        "AccessId": 202025,
        "FetterGroupDesc": "PrefabTextItem_Empty_Text",
        "FetterElementColor": "FFFFFF00",
        "FetterElementPath": "/Game/Aki/UI/UIResources/Common/Image/IconElementAttri/T_IconElementAttriSupport.T_IconElementAttriSupport"
      },
      "Fetter": null
    }
  ],
  "FetterDetails": {
    "息界同調之律": {
      "EffectDescriptions": [
        "角色施放聲骸技能時，自身重擊傷害加成提升30%，持續4秒；隊伍中角色聲骸技能傷害加成提升4%，該效果可疊加4層，持續30秒，同名聲骸僅可觸發1次該效果，效果消失時重置同名聲骸記錄，4層時施放聲骸技能可刷新持續時間。"
      ],
      "DefineDescriptions": [
        "看似平靜卻暗藏力量的和鳴，屬於能執掌雷電的強者。風暴不會發出警告，但沒人能忽視它的先兆。"
      ]
    }
  }
}