{
  "Id": 26010001,
  "ItemId": 0,
  "Type": 3,
  "Title": "จดหมายจากวังแห่งเอฟอร์",
  "Text": "ถึงกลาดิเอเตอร์ Lord Aeolus<br><br>ข้าได้รับคำขอถอนตัวของท่านแล้ว และต้องขอปฏิเสธคำร้องนั้น เกียรติยศแห่งเซปติมอนต์จะสถิตอยู่กับท่าน ผู้เป็นกลาดิเอเตอร์ที่แท้จริง ชั่วนิรันดร์<br><br>อีกเรื่องหนึ่ง ท่าน Aeolus ท่านคือคู่ต่อกรที่น่าเกรงขามลำดับที่เจ็ดบนเส้นทางสู่บัลลังก์ของข้า เพลงดาบและสัญชาตญาณอันเฉียบคมในสนามรบของท่านยังตราตรึงในใจข้ามิเคยลืม ข้าจะขอแบกรับไว้ซึ่งคมดาบ อุดมการณ์ และทุกสิ่งที่ท่านเคยยึดมั่น เพื่อนำพาเซปติมอนต์ไปสู่ความรุ่งโรจน์<br><br>ขอท่านจงเป็นพยาน<br><br>ด้วยความเคารพ<br>เอฟอร์ ออกัสตา แห่งเซปติมอนต์",
  "Picture": [],
  "Audio": "",
  "Background": "",
  "EntryAudio": "",
  "ExitAudio": "",
  "Source": "แดนรกร้าง - 11422, 13699, 94"
}