{
  "Id": 139000021,
  "Name": "銀髪の音骸トレーナー・三",
  "Description": "景燭おじいちゃんが、ついに音骸トレーニングの究極の極意を出した……！今度こそ、彼は願いをかなえることができるだろうか。",
  "MaleTexture": "",
  "FemaleTexture": "",
  "AreaIcon": "",
  "QuestId": 139000021,
  "ShowQuestList": [],
  "QuestDesc": "景燭おじいちゃんが、ついに音骸トレーニングの究極の極意を出した……！今度こそ、彼は願いをかなえることができるだろうか。",
  "Conditions": [
    {
      "Type": "PreQuest",
      "PreQuest": 139000020,
      "PreQuestName": "銀髪の音骸トレーナー・二"
    },
    {
      "Type": "ExploreLevel",
      "ExploreLevel": 21
    }
  ],
  "Chapters": [
    {
      "Dialogues": [
        {
          "Id": 1,
          "Speaker": "景燭（ケイショク）",
          "PlotLineKey": "ぜぇ……ぜぇ……この辺りだな。",
          "PlayVoice": false,
          "Options": []
        },
        {
          "Id": 2,
          "Speaker": "景燭（ケイショク）",
          "PlotLineKey": "俺は少し……休まねぇと……<br>後はあんたら若者の出番、だな……",
          "PlayVoice": false,
          "Options": []
        }
      ]
    },
    {
      "Dialogues": [
        {
          "Id": 1,
          "Speaker": "景燭（ケイショク）",
          "PlotLineKey": "おかしい……この時間帯なら、外で日向ぼっこしてるはず……中にいるのか？",
          "PlayVoice": false,
          "Options": []
        },
        {
          "Id": 2,
          "Speaker": "景燭（ケイショク）",
          "PlotLineKey": "いない……",
          "PlayVoice": false,
          "Options": [
            {
              "TextId": 323,
              "PlotLineKey": "出掛けたのでは？",
              "PlayVoice": false,
              "JumpToId": 3
            }
          ]
        },
        {
          "Id": 3,
          "Speaker": "景燭（ケイショク）",
          "PlotLineKey": "いや、凌寒さんは外に出られないんだ。何せ、もう家に帰る道も覚えていないから……",
          "PlayVoice": false,
          "Options": [],
          "JumpToId": 4
        },
        {
          "Id": 4,
          "Speaker": "熾霞（シカ）",
          "PlotLineKey": "それは心配だね……",
          "PlayVoice": false,
          "Options": []
        },
        {
          "Id": 5,
          "Speaker": "熾霞（シカ）",
          "PlotLineKey": "ここいらじゃあたしもそこそこわかるから。<br>凌寒ばあちゃんを見た人はないか、今すぐ聞いてくるね。",
          "PlayVoice": false,
          "Options": []
        }
      ]
    },
    {
      "Dialogues": [
        {
          "Id": 1,
          "Speaker": "熾霞（シカ）",
          "PlotLineKey": "この一帯は危ないし、凌寒ばあちゃんの体もよくないし……<br>どうしてここに来るんだろう……",
          "PlayVoice": false,
          "Options": []
        },
        {
          "Id": 2,
          "Speaker": "景燭（ケイショク）",
          "PlotLineKey": "今日は……特別な日だからな。",
          "PlayVoice": false,
          "Options": [
            {
              "TextId": 407,
              "PlotLineKey": "特別？",
              "PlayVoice": false,
              "JumpToId": 3
            }
          ]
        },
        {
          "Id": 3,
          "Speaker": "景燭（ケイショク）",
          "PlotLineKey": "何年前かの今日……今州は激しい残像潮に見舞われた。前線で戦う夜帰が、一人で数百体の残像を対峙しなければいけない、絶望的な状況だった。",
          "PlayVoice": false,
          "Options": [],
          "JumpToId": 4
        },
        {
          "Id": 4,
          "Speaker": "景燭（ケイショク）",
          "PlotLineKey": "その絶望を打破するため、策を打ち出したのが凌寒だ。音骸に詳しい彼女は、音骸を使った計画を提案した。",
          "PlayVoice": false,
          "Options": []
        },
        {
          "Id": 5,
          "Speaker": "景燭（ケイショク）",
          "PlotLineKey": "今日は……チーム全員が一緒に、この場所で数百体の「宣諭の楽手」の音骸を集めた日……",
          "PlayVoice": false,
          "Options": [
            {
              "TextId": 408,
              "PlotLineKey": "彼女も夜帰の戦士だった？",
              "PlayVoice": false,
              "JumpToId": 6
            }
          ]
        },
        {
          "Id": 6,
          "Speaker": "景燭（ケイショク）",
          "PlotLineKey": "そうだ……",
          "PlayVoice": false,
          "Options": [],
          "JumpToId": 7
        },
        {
          "Id": 7,
          "Speaker": "熾霞（シカ）",
          "PlotLineKey": "あれ？あそこの女の人……凌寒ばあちゃんだ！凌寒ばあちゃん～！",
          "PlayVoice": false,
          "Options": []
        },
        {
          "Id": 8,
          "Speaker": "熾霞（シカ）",
          "PlotLineKey": "遠くて全然聞こえてない！",
          "PlayVoice": false,
          "Options": []
        },
        {
          "Id": 9,
          "Speaker": "景燭（ケイショク）",
          "PlotLineKey": "……まずい！残像があそこに集まってる！",
          "PlayVoice": false,
          "Options": []
        },
        {
          "Id": 10,
          "Speaker": "熾霞（シカ）",
          "PlotLineKey": "しまった……！この距離じゃ間に合わない……！",
          "PlayVoice": false,
          "Options": []
        },
        {
          "Id": 11,
          "Speaker": "景燭（ケイショク）",
          "PlotLineKey": "俺に任せろ……！",
          "PlayVoice": false,
          "Options": []
        },
        {
          "Id": 12,
          "Speaker": "景燭（ケイショク）",
          "PlotLineKey": "いけ！寒霜亀！凌寒を守ってくれ！",
          "PlayVoice": false,
          "Options": []
        },
        {
          "Id": 13,
          "Speaker": "熾霞（シカ）",
          "PlotLineKey": "や……やったよ！何とか助かった……！",
          "PlayVoice": false,
          "Options": [
            {
              "TextId": 427,
              "PlotLineKey": "今がチャンス！",
              "PlayVoice": false,
              "JumpToId": 14
            }
          ]
        },
        {
          "Id": 14,
          "Speaker": "景燭（ケイショク）",
          "PlotLineKey": "いい観察眼だ。あんた、夜帰に向いてるな。",
          "PlayVoice": false,
          "Options": [],
          "JumpToId": 15
        },
        {
          "Id": 15,
          "Speaker": "熾霞（シカ）",
          "PlotLineKey": "やってやる！",
          "PlayVoice": false,
          "Options": []
        }
      ]
    },
    {
      "Dialogues": [
        {
          "Id": 1,
          "Speaker": "熾霞（シカ）",
          "PlotLineKey": "ふぅ……ようやく片付けた……",
          "PlayVoice": false,
          "Options": []
        },
        {
          "Id": 2,
          "Speaker": "景燭（ケイショク）",
          "PlotLineKey": "若者たち、大丈夫か？",
          "PlayVoice": false,
          "Options": []
        },
        {
          "Id": 3,
          "Speaker": "熾霞（シカ）",
          "PlotLineKey": "へ、平気っ！安心して、少し腰が抜けちゃって……",
          "PlayVoice": false,
          "Options": []
        },
        {
          "Id": 4,
          "Speaker": "熾霞（シカ）",
          "PlotLineKey": "それより、凌寒ばあちゃんの様子はどう？",
          "PlayVoice": false,
          "Options": []
        }
      ]
    },
    {
      "Dialogues": [
        {
          "Id": 1,
          "Speaker": "景燭（ケイショク）",
          "PlotLineKey": "凌寒……どうした？怪我はないか？<br>どこが痛い？",
          "PlayVoice": false,
          "Options": []
        },
        {
          "Id": 2,
          "Speaker": "凌寒（リンカン）",
          "PlotLineKey": "この音骸は……寒霜亀……",
          "PlayVoice": false,
          "Options": []
        },
        {
          "Id": 3,
          "Speaker": "凌寒（リンカン）",
          "PlotLineKey": "音骸も……音骸を使う腕も、一流だね……",
          "PlayVoice": false,
          "Options": []
        },
        {
          "Id": 4,
          "Speaker": "景燭（ケイショク）",
          "PlotLineKey": "凌寒……",
          "PlayVoice": false,
          "Options": []
        },
        {
          "Id": 5,
          "Speaker": "凌寒（リンカン）",
          "PlotLineKey": "この音骸を見ると、何故か……「あの人」を思い出す……",
          "PlayVoice": false,
          "Options": []
        },
        {
          "Id": 6,
          "Speaker": "凌寒（リンカン）",
          "PlotLineKey": "冴えない寒霜亀で、チームの全員を守った「あの人」……",
          "PlayVoice": false,
          "Options": []
        },
        {
          "Id": 7,
          "Speaker": "凌寒（リンカン）",
          "PlotLineKey": "最初は彼と、彼の寒霜亀を小馬鹿にした人たちも……あれから何も言えなくなった……",
          "PlayVoice": false,
          "Options": []
        },
        {
          "Id": 8,
          "Speaker": "凌寒（リンカン）",
          "PlotLineKey": "音骸に絶対的な強弱なんてない。要は、使い手の腕次第……",
          "PlayVoice": false,
          "Options": []
        },
        {
          "Id": 9,
          "Speaker": "景燭（ケイショク）",
          "PlotLineKey": "そうか……そうだったな……俺としたことが……遠回りしてしまったな……",
          "PlayVoice": false,
          "Options": []
        },
        {
          "Id": 10,
          "Speaker": "熾霞（シカ）",
          "PlotLineKey": "景燭じいちゃん、何で泣いてるの？",
          "PlayVoice": false,
          "Options": []
        },
        {
          "Id": 11,
          "Speaker": "景燭（ケイショク）",
          "PlotLineKey": "これは……嬉しくてな……",
          "PlayVoice": false,
          "Options": []
        },
        {
          "Id": 12,
          "Speaker": "凌寒（リンカン）",
          "PlotLineKey": "そう言えば、あなた……「あの人」と似てるわね。",
          "PlayVoice": false,
          "Options": []
        },
        {
          "Id": 13,
          "Speaker": "凌寒（リンカン）",
          "PlotLineKey": "鼻が一つで目が二つ。ええ、似てるとも。",
          "PlayVoice": false,
          "Options": []
        },
        {
          "Id": 14,
          "Speaker": "凌寒（リンカン）",
          "PlotLineKey": "でも、カッコよさじゃまだまだだわ。「あの人」は無敵の英雄……どんな人とも比べられない……",
          "PlayVoice": false,
          "Options": []
        },
        {
          "Id": 15,
          "Speaker": "景燭（ケイショク）",
          "PlotLineKey": "あんたの老眼も……案外ひどいもんだな……",
          "PlayVoice": false,
          "Options": [
            {
              "TextId": 451,
              "PlotLineKey": "話しかけるチャンス！",
              "PlayVoice": false,
              "JumpToId": 16
            }
          ]
        },
        {
          "Id": 16,
          "Speaker": "景燭（ケイショク）",
          "PlotLineKey": "ああそうか！まずは自己紹介だな。凌寒隊長！俺は夜帰<ano=先鋒>破陣</ano>の戦士……景燭！",
          "PlayVoice": false,
          "Options": [],
          "JumpToId": 17
        },
        {
          "Id": 17,
          "Speaker": "凌寒（リンカン）",
          "PlotLineKey": "景燭か……そういえば、花を持っていたようだが？",
          "PlayVoice": false,
          "Options": []
        },
        {
          "Id": 18,
          "Speaker": "景燭（ケイショク）",
          "PlotLineKey": "……花か！ああ、持ってる！……って、ない？さっき音骸を使った時にどこかに落としたのか……",
          "PlayVoice": false,
          "Options": [
            {
              "TextId": 452,
              "PlotLineKey": "探してくる！",
              "PlayVoice": false,
              "JumpToId": 19
            }
          ]
        },
        {
          "Id": 19,
          "Speaker": "熾霞（シカ）",
          "PlotLineKey": "あそこよ。早く持ってて！",
          "PlayVoice": false,
          "Options": []
        }
      ]
    },
    {
      "Dialogues": [
        {
          "Id": 1,
          "Speaker": "熾霞（シカ）",
          "PlotLineKey": "おお！待たせたな！",
          "PlayVoice": false,
          "Options": []
        },
        {
          "Id": 2,
          "Speaker": "熾霞（シカ）",
          "PlotLineKey": "景燭じいちゃんの件だって聞いて、一番乗りのつもりで来たんだけど……",
          "PlayVoice": false,
          "Options": []
        },
        {
          "Id": 3,
          "Speaker": "景燭（ケイショク）",
          "PlotLineKey": "そんなに急がなくても大丈夫だ。",
          "PlayVoice": false,
          "Options": []
        },
        {
          "Id": 4,
          "Speaker": "熾霞（シカ）",
          "PlotLineKey": "ありがと、じいちゃん。それじゃあ早速、今回の計画を聞かせてよ！",
          "PlayVoice": false,
          "Options": []
        },
        {
          "Id": 5,
          "Speaker": "景燭（ケイショク）",
          "PlotLineKey": "{PlayerName}の意見は最もだ。まずは話題を見つけ、少しづつ関係を築く……",
          "PlayVoice": false,
          "Options": []
        },
        {
          "Id": 6,
          "Speaker": "景燭（ケイショク）",
          "PlotLineKey": "だが、音骸を強化する方法をもう一個思い出した。",
          "PlayVoice": false,
          "Options": [
            {
              "TextId": 299,
              "PlotLineKey": "どんな方法？",
              "PlayVoice": false,
              "JumpToId": null
            }
          ]
        },
        {
          "Id": 7,
          "Speaker": "熾霞（シカ）",
          "PlotLineKey": "まだ何か手があるの？あたしから見れば十分強いのに……",
          "PlayVoice": false,
          "Options": []
        },
        {
          "Id": 8,
          "Speaker": "景燭（ケイショク）",
          "PlotLineKey": "それがあるんだ。無音区の中に……「チュナ」と呼ばれるものが！",
          "PlayVoice": false,
          "Options": []
        },
        {
          "Id": 9,
          "Speaker": "熾霞（シカ）",
          "PlotLineKey": "ちゅな？",
          "PlayVoice": false,
          "Options": []
        },
        {
          "Id": 10,
          "Speaker": "景燭（ケイショク）",
          "PlotLineKey": "そう。チュナは音骸の周波数を調整し、不要な雑音を除去できる。これで音骸はもっと強くなる！",
          "PlayVoice": false,
          "Options": []
        },
        {
          "Id": 11,
          "Speaker": "熾霞（シカ）",
          "PlotLineKey": "そうか、あの変な形をしたあれか！",
          "PlayVoice": false,
          "Options": []
        },
        {
          "Id": 12,
          "Speaker": "景燭（ケイショク）",
          "PlotLineKey": "だから、次は無音区を探してチュナを入手し……",
          "PlayVoice": false,
          "Options": []
        },
        {
          "Id": 13,
          "Speaker": "熾霞（シカ）",
          "PlotLineKey": "よっしゃー！音骸強化のために、出発！",
          "PlayVoice": false,
          "Options": []
        }
      ]
    },
    {
      "Dialogues": [
        {
          "Id": 1,
          "Speaker": "熾霞（シカ）",
          "PlotLineKey": "韶華さん、今日は凌寒ばあちゃんを見なかった？",
          "PlayVoice": false,
          "Options": []
        },
        {
          "Id": 2,
          "Speaker": "韶華（ショウカ）",
          "PlotLineKey": "となりのおばあさんね……",
          "PlayVoice": false,
          "Options": []
        },
        {
          "Id": 3,
          "Speaker": "韶華（ショウカ）",
          "PlotLineKey": "今日は朝から出かけてた気がする……",
          "PlayVoice": false,
          "Options": []
        },
        {
          "Id": 4,
          "Speaker": "韶華（ショウカ）",
          "PlotLineKey": "でもおかしいわね。普段は病気で外に出られないはず……日向ぼっこしてるところはよく見るけど……",
          "PlayVoice": false,
          "Options": []
        },
        {
          "Id": 5,
          "Speaker": "韶華（ショウカ）",
          "PlotLineKey": "なのに、今朝はそのまま行ってしまった……行き先も見当がつかないわね……",
          "PlayVoice": false,
          "Options": []
        },
        {
          "Id": 6,
          "Speaker": "熾霞（シカ）",
          "PlotLineKey": "ありがとう、韶華さん。",
          "PlayVoice": false,
          "Options": []
        }
      ]
    },
    {
      "Dialogues": [
        {
          "Id": 1,
          "Speaker": "熾霞（シカ）",
          "PlotLineKey": "どうも。名前を伺っても？",
          "PlayVoice": false,
          "Options": []
        },
        {
          "Id": 2,
          "Speaker": "攬清（ランセイ）",
          "PlotLineKey": "あ、どうも。最近ここに越してきた攬清（らんせい）です。その身なりは、今巡尉ですね。何かありましたか？",
          "PlayVoice": false,
          "Options": []
        },
        {
          "Id": 3,
          "Speaker": "熾霞（シカ）",
          "PlotLineKey": "聞きたい事があって……今日、凌寒ばあちゃんを見なかった？",
          "PlayVoice": false,
          "Options": []
        },
        {
          "Id": 4,
          "Speaker": "攬清（ランセイ）",
          "PlotLineKey": "あのおばあさんですか？今日は見てないですね……",
          "PlayVoice": false,
          "Options": []
        },
        {
          "Id": 5,
          "Speaker": "攬清（ランセイ）",
          "PlotLineKey": "まだそんなに会ったことはないのですが、とても気品のあるおばあさんですよね。",
          "PlayVoice": false,
          "Options": []
        },
        {
          "Id": 6,
          "Speaker": "攬清（ランセイ）",
          "PlotLineKey": "しかし、いつ見てもどこか疲れてるようで……記憶力も、あまりよくないご様子。",
          "PlayVoice": false,
          "Options": []
        },
        {
          "Id": 7,
          "Speaker": "攬清（ランセイ）",
          "PlotLineKey": "酷い病気だと聞いています……大変ですね。",
          "PlayVoice": false,
          "Options": []
        }
      ]
    },
    {
      "Dialogues": [
        {
          "Id": 1,
          "Speaker": "瑩瑩（エイエイ）",
          "PlotLineKey": "じっちゃん！うう……もう大変なの……うう……",
          "PlayVoice": false,
          "Options": []
        }
      ]
    },
    {
      "Dialogues": [
        {
          "Id": 1,
          "Speaker": "景燭（ケイショク）",
          "PlotLineKey": "さあ、この夜息草を受け取ってほしい……凌寒さん、もう一度、俺の伴侶になってくれないか？",
          "PlayVoice": false,
          "Options": []
        },
        {
          "Id": 0,
          "Speaker": "Speaker_83",
          "PlotLineKey": "",
          "PlayVoice": false,
          "Options": []
        },
        {
          "Id": 2,
          "Speaker": "凌寒（リンカン）",
          "PlotLineKey": "夜息草……いい香りね。彼も昔、よくこれを贈ってくれたわ。私、この花の香りがとてもなの。",
          "PlayVoice": false,
          "Options": []
        },
        {
          "Id": 3,
          "Speaker": "凌寒（リンカン）",
          "PlotLineKey": "私にとって、花も音骸も同じ。自分に似合うものが一番。",
          "PlayVoice": false,
          "Options": []
        },
        {
          "Id": 4,
          "Speaker": "景燭（ケイショク）",
          "PlotLineKey": "ああ、そうだとも！これからは、あんたの隣で日向ぼっこして、お喋りして……好きな事を一緒にしよう！",
          "PlayVoice": false,
          "Options": []
        },
        {
          "Id": 5,
          "Speaker": "景燭（ケイショク）",
          "PlotLineKey": "あんたの隣で、一緒に過ごしたいんだ！",
          "PlayVoice": false,
          "Options": []
        },
        {
          "Id": 6,
          "Speaker": "景燭（ケイショク）",
          "PlotLineKey": "それに、俺は約束したはずだ。絶対にあんたを一人にさせない。この景燭の約束だぞ！絶対に最後までやり遂げてみせる！",
          "PlayVoice": false,
          "Options": []
        },
        {
          "Id": 7,
          "Speaker": "凌寒（リンカン）",
          "PlotLineKey": "でも、ここじゃ日向ぼっこはできないわね。",
          "PlayVoice": false,
          "Options": []
        },
        {
          "Id": 8,
          "Speaker": "凌寒（リンカン）",
          "PlotLineKey": "一緒に帰りましょう。うちの庭の日差しは最高だからね。",
          "PlayVoice": false,
          "Options": []
        },
        {
          "Id": 9,
          "Speaker": "景燭（ケイショク）",
          "PlotLineKey": "ああ……勿論だ！一緒に帰ろう！",
          "PlayVoice": false,
          "Options": []
        }
      ]
    },
    {
      "Dialogues": [
        {
          "Id": 1,
          "Speaker": "熾霞（シカ）",
          "PlotLineKey": "景燭じいちゃん。凌寒ばあちゃんは？",
          "PlayVoice": false,
          "Options": []
        },
        {
          "Id": 2,
          "Speaker": "景燭（ケイショク）",
          "PlotLineKey": "彼女の体調が心配だったからな、先に部屋で休ませた。",
          "PlayVoice": false,
          "Options": []
        },
        {
          "Id": 3,
          "Speaker": "熾霞（シカ）",
          "PlotLineKey": "そっか、とりあえず無事だったんだね。ならよかった……",
          "PlayVoice": false,
          "Options": []
        },
        {
          "Id": 4,
          "Speaker": "熾霞（シカ）",
          "PlotLineKey": "でも……あたしはまだまだ聞きたい事がたくさんある。{PlayerName}……あんたもだよな？",
          "PlayVoice": false,
          "Options": [
            {
              "TextId": 489,
              "PlotLineKey": "確かに……",
              "PlayVoice": false,
              "JumpToId": 5
            }
          ]
        },
        {
          "Id": 5,
          "Speaker": "景燭（ケイショク）",
          "PlotLineKey": "そうだな……もう察してはいるだろうが……凌寒は優秀な夜帰の戦士、破陣で小隊長を務めた人だ。",
          "PlayVoice": false,
          "Options": [],
          "JumpToId": 6
        },
        {
          "Id": 6,
          "Speaker": "景燭（ケイショク）",
          "PlotLineKey": "それに、俺の立派な妻でもあった……",
          "PlayVoice": false,
          "Options": []
        },
        {
          "Id": 7,
          "Speaker": "景燭（ケイショク）",
          "PlotLineKey": "隊長として、身に余る責任をたくさん、負ってきたんだ。いつも最前線で戦い、隊員を守り、俺たちに生き残る術を教えてくれた。",
          "PlayVoice": false,
          "Options": []
        },
        {
          "Id": 8,
          "Speaker": "景燭（ケイショク）",
          "PlotLineKey": "だが、そんな戦い方を続けた結果、彼女の体はボロボロになっていった。",
          "PlayVoice": false,
          "Options": []
        },
        {
          "Id": 9,
          "Speaker": "景燭（ケイショク）",
          "PlotLineKey": "そして、ある大戦の勝利後……彼女は倒れた。そこからか……病気で意識がぼやけ、色んな事を忘れ始めた。",
          "PlayVoice": false,
          "Options": []
        },
        {
          "Id": 10,
          "Speaker": "景燭（ケイショク）",
          "PlotLineKey": "長年守ってきた今州の道を忘れて、大好きだった鍋魁の食べ方も忘れて……そして……",
          "PlayVoice": false,
          "Options": []
        },
        {
          "Id": 11,
          "Speaker": "景燭（ケイショク）",
          "PlotLineKey": "俺の事も、忘れてしまった……",
          "PlayVoice": false,
          "Options": []
        },
        {
          "Id": 12,
          "Speaker": "熾霞（シカ）",
          "PlotLineKey": "そっか……だから景燭じいちゃんは、凌寒ばあちゃんを追ってたのか……",
          "PlayVoice": false,
          "Options": []
        },
        {
          "Id": 13,
          "Speaker": "熾霞（シカ）",
          "PlotLineKey": "もう一度、夫として妻の隣にいるために……",
          "PlayVoice": false,
          "Options": []
        },
        {
          "Id": 14,
          "Speaker": "景燭（ケイショク）",
          "PlotLineKey": "それに……強者揃いだった俺たちの小隊も、今や俺たちだけ……",
          "PlayVoice": false,
          "Options": []
        },
        {
          "Id": 15,
          "Speaker": "景燭（ケイショク）",
          "PlotLineKey": "それで、俺のことまで忘れちまったら……彼女は本当に一人なってしまう！こんな事……俺は決して許せないっ！",
          "PlayVoice": false,
          "Options": []
        },
        {
          "Id": 16,
          "Speaker": "景燭（ケイショク）",
          "PlotLineKey": "はっ……すまない、また気が立ってしまった。悪いな……凌寒を取り戻したばかりなのに……",
          "PlayVoice": false,
          "Options": []
        },
        {
          "Id": 17,
          "Speaker": "景燭（ケイショク）",
          "PlotLineKey": "でも、ようやく彼女に認めてもらった。これほど喜ばしいことはない！",
          "PlayVoice": false,
          "Options": []
        },
        {
          "Id": 18,
          "Speaker": "景燭（ケイショク）",
          "PlotLineKey": "過去は変えられない……だからこそ、これから彼女と一緒に過ごす一分一秒を、大事に噛み締めて生きていくんだ！",
          "PlayVoice": false,
          "Options": []
        },
        {
          "Id": 19,
          "Speaker": "熾霞（シカ）",
          "PlotLineKey": "あたしたちも今を大事に生きて……全力で頑張らないと！",
          "PlayVoice": false,
          "Options": []
        },
        {
          "Id": 20,
          "Speaker": "景燭（ケイショク）",
          "PlotLineKey": "ああ、その調子だ！また暇があったら遊びに来てくれ。いつでも音骸について教えてやろう。",
          "PlayVoice": false,
          "Options": []
        },
        {
          "Id": 21,
          "Speaker": "景燭（ケイショク）",
          "PlotLineKey": "何せ今回丸く収まったのは、お前らのおかげだからな。",
          "PlayVoice": false,
          "Options": []
        },
        {
          "Id": 22,
          "Speaker": "景燭（ケイショク）",
          "PlotLineKey": "それに……死力を尽くして守った次世代が、これほど健やかに成長し、時代を支えてくれていると知れば、きっと彼女も喜ぶに違いない。",
          "PlayVoice": false,
          "Options": []
        },
        {
          "Id": 23,
          "Speaker": "景燭（ケイショク）",
          "PlotLineKey": "では改めて……本当にありがとうな。さあ、これは報酬だ。",
          "PlayVoice": false,
          "Options": []
        },
        {
          "Id": 24,
          "Speaker": "景燭（ケイショク）",
          "PlotLineKey": "それと……最後にもう一つ忠告がある。",
          "PlayVoice": false,
          "Options": []
        },
        {
          "Id": 25,
          "Speaker": "景燭（ケイショク）",
          "PlotLineKey": "音骸を使いこなすんだ。外には危険が多い……若者のお前らには、いずれ本当の試練が来る。",
          "PlayVoice": false,
          "Options": []
        },
        {
          "Id": 26,
          "Speaker": "景燭（ケイショク）",
          "PlotLineKey": "その日が来たら……自分を、そして大事な人を、必ず守り抜け。",
          "PlayVoice": false,
          "Options": []
        }
      ]
    },
    {
      "Dialogues": [
        {
          "Id": 1,
          "Speaker": "景燭（ケイショク）",
          "PlotLineKey": "悪くない！昔の俺とかなり似てきた！",
          "PlayVoice": false,
          "Options": []
        },
        {
          "Id": 2,
          "Speaker": "景燭（ケイショク）",
          "PlotLineKey": "これを見れば、凌寒さんもイチコロだろう！",
          "PlayVoice": false,
          "Options": []
        },
        {
          "Id": 3,
          "Speaker": "景燭（ケイショク）",
          "PlotLineKey": "早速、帰って見せてやろう。",
          "PlayVoice": false,
          "Options": []
        }
      ]
    },
    {
      "Dialogues": [
        {
          "Id": 9,
          "Speaker": "熾霞（シカ）",
          "PlotLineKey": "さすが最新鋭技術。もう見つかったね。",
          "PlayVoice": false,
          "Options": []
        },
        {
          "Id": 10,
          "Speaker": "景燭（ケイショク）",
          "PlotLineKey": "行こう！<br>凌寒……持ち堪えろよ！",
          "PlayVoice": false,
          "Options": []
        }
      ]
    }
  ]
}