{
  "17": {
    "1": {
      "1": {
        "1": [
          {
            "id": 179,
            "instanceId": 20013,
            "season": 17,
            "areaNum": 1,
            "floor": 1,
            "cost": 1,
            "difficulty": 3,
            "areaName": "หอคอยเรโซแนนซ์",
            "monsters": [
              {
                "id": 310000430,
                "name": "Fae Ignis",
                "rarity": {
                  "id": 1,
                  "desc": "ระดับมาตรฐาน (ขุมพลัง 1)"
                },
                "icon": "https://api.encore.moe/resource/Data/Game/Aki/UI/UIResources/Common/Image/IconMonsterHead/T_IconMonsterHead_31043_UI.png",
                "elements": [
                  {
                    "id": 6,
                    "name": "ฮาว็อค",
                    "icon": "https://api.encore.moe/resource/Data/Game/Aki/UI/UIResources/Common/Image/IconElement/T_IconElementDark2.png"
                  }
                ]
              },
              {
                "id": 310000450,
                "name": "Hocus Pocus",
                "rarity": {
                  "id": 1,
                  "desc": "ระดับมาตรฐาน (ขุมพลัง 1)"
                },
                "icon": "https://api.encore.moe/resource/Data/Game/Aki/UI/UIResources/Common/Image/IconMonsterHead/T_IconMonsterHead_31045_UI.png",
                "elements": [
                  {
                    "id": 6,
                    "name": "ฮาว็อค",
                    "icon": "https://api.encore.moe/resource/Data/Game/Aki/UI/UIResources/Common/Image/IconElement/T_IconElementDark2.png"
                  }
                ]
              }
            ],
            "buffs": [
              {
                "id": 92007114,
                "name": "",
                "desc": "<span style=\"color:#f8e56cff;\">ความต้านทานดาเมจสเปกโตร</span>ของศัตรูลดลง 10%",
                "icon": "https://api.encore.moe/resource/Data/Game/Aki/UI/UIResources/Common/Image/IconAttribute/T_Iconpropertyredattack_UI.png"
              },
              {
                "id": 92008034,
                "name": "",
                "desc": "เมื่อเรโซเนเตอร์ให้การรักษาสมาชิกในทีม การฟื้นฟูพลังงานของเขาจะเพิ่มขึ้น 20% ระยะเวลา 4 วินาที เมื่อเรโซเนเตอร์ได้รับการรักษา Crit. DMG ของเขาจะเพิ่มขึ้น 30% ระยะเวลา 4 วินาที การทริกเกอร์เอฟเฟกต์ซ้ำจะรีเซ็ตระยะเวลาของเอฟเฟกต์",
                "icon": "https://api.encore.moe/resource/Data/Game/Aki/UI/UIResources/Common/Image/IconAttribute/T_Iconpropertyredattack_UI.png"
              }
            ],
            "targets": [
              {
                "id": 1,
                "score": 0,
                "desc": "ผ่านการท้าทาย",
                "rawDesc": "ผ่านการท้าทาย",
                "params": [
                  0
                ]
              },
              {
                "id": 2,
                "score": 90,
                "desc": "ผ่านการท้าทายในเวลาเหลืออย่างน้อย <span style=\"color:#ffd12f;font-weight:bold\">90</span> วินาที",
                "rawDesc": "ผ่านการท้าทายในเวลาเหลืออย่างน้อย {0} วินาที",
                "params": [
                  90
                ]
              },
              {
                "id": 3,
                "score": 150,
                "desc": "ผ่านการท้าทายในเวลาเหลืออย่างน้อย <span style=\"color:#ffd12f;font-weight:bold\">150</span> วินาที",
                "rawDesc": "ผ่านการท้าทายในเวลาเหลืออย่างน้อย {0} วินาที",
                "params": [
                  150
                ]
              }
            ],
            "bgPath": "https://api.encore.moe/resource/Data/Game/Aki/UI/UIResources/UiDailyTower/Image/T_loopTowerBg01_UI_png.png",
            "itemBgPath": "https://api.encore.moe/resource/Data/Game/Aki/UI/UIResources/UiDailyTower/Image/T_DailyTowerL1.png"
          }
        ]
      },
      "2": {
        "2": [
          {
            "id": 180,
            "instanceId": 20014,
            "season": 17,
            "areaNum": 1,
            "floor": 2,
            "cost": 2,
            "difficulty": 3,
            "areaName": "หอคอยเรโซแนนซ์",
            "monsters": [
              {
                "id": 310000470,
                "name": "Diggy Duggy",
                "rarity": {
                  "id": 1,
                  "desc": "ระดับมาตรฐาน (ขุมพลัง 1)"
                },
                "icon": "https://api.encore.moe/resource/Data/Game/Aki/UI/UIResources/Common/Image/IconMonsterHead/T_IconMonsterHead_31047_UI.png",
                "elements": [
                  {
                    "id": 0,
                    "name": "กายภาพ",
                    "icon": "https://api.encore.moe/resource/Data/Game/Aki/UI/UIResources/Common/Image/IconElement/T_IconElementZero2.png"
                  }
                ]
              },
              {
                "id": 320000300,
                "name": "Cuddle Wuddle",
                "rarity": {
                  "id": 2,
                  "desc": "ระดับอีลีท (ขุมพลัง 3)"
                },
                "icon": "https://api.encore.moe/resource/Data/Game/Aki/UI/UIResources/Common/Image/IconMonsterHead/T_IconMonsterHead_32030_UI.png",
                "elements": [
                  {
                    "id": 0,
                    "name": "กายภาพ",
                    "icon": "https://api.encore.moe/resource/Data/Game/Aki/UI/UIResources/Common/Image/IconElement/T_IconElementZero2.png"
                  }
                ]
              }
            ],
            "buffs": [
              {
                "id": 92007114,
                "name": "",
                "desc": "<span style=\"color:#f8e56cff;\">ความต้านทานดาเมจสเปกโตร</span>ของศัตรูลดลง 10%",
                "icon": "https://api.encore.moe/resource/Data/Game/Aki/UI/UIResources/Common/Image/IconAttribute/T_Iconpropertyredattack_UI.png"
              },
              {
                "id": 92008034,
                "name": "",
                "desc": "เมื่อเรโซเนเตอร์ให้การรักษาสมาชิกในทีม การฟื้นฟูพลังงานของเขาจะเพิ่มขึ้น 20% ระยะเวลา 4 วินาที เมื่อเรโซเนเตอร์ได้รับการรักษา Crit. DMG ของเขาจะเพิ่มขึ้น 30% ระยะเวลา 4 วินาที การทริกเกอร์เอฟเฟกต์ซ้ำจะรีเซ็ตระยะเวลาของเอฟเฟกต์",
                "icon": "https://api.encore.moe/resource/Data/Game/Aki/UI/UIResources/Common/Image/IconAttribute/T_Iconpropertyredattack_UI.png"
              }
            ],
            "targets": [
              {
                "id": 1,
                "score": 0,
                "desc": "ผ่านการท้าทาย",
                "rawDesc": "ผ่านการท้าทาย",
                "params": [
                  0
                ]
              },
              {
                "id": 2,
                "score": 90,
                "desc": "ผ่านการท้าทายในเวลาเหลืออย่างน้อย <span style=\"color:#ffd12f;font-weight:bold\">90</span> วินาที",
                "rawDesc": "ผ่านการท้าทายในเวลาเหลืออย่างน้อย {0} วินาที",
                "params": [
                  90
                ]
              },
              {
                "id": 3,
                "score": 150,
                "desc": "ผ่านการท้าทายในเวลาเหลืออย่างน้อย <span style=\"color:#ffd12f;font-weight:bold\">150</span> วินาที",
                "rawDesc": "ผ่านการท้าทายในเวลาเหลืออย่างน้อย {0} วินาที",
                "params": [
                  150
                ]
              }
            ],
            "bgPath": "https://api.encore.moe/resource/Data/Game/Aki/UI/UIResources/UiDailyTower/Image/T_loopTowerBg02_UI_png.png",
            "itemBgPath": "https://api.encore.moe/resource/Data/Game/Aki/UI/UIResources/UiDailyTower/Image/T_DailyTowerL2.png"
          }
        ]
      },
      "3": {
        "3": [
          {
            "id": 181,
            "instanceId": 20015,
            "season": 17,
            "areaNum": 1,
            "floor": 3,
            "cost": 3,
            "difficulty": 3,
            "areaName": "หอคอยเรโซแนนซ์",
            "monsters": [
              {
                "id": 310000290,
                "name": "พลขว้างแฟรกต์ซิดัส",
                "rarity": {
                  "id": 1,
                  "desc": "ระดับมาตรฐาน (ขุมพลัง 1)"
                },
                "icon": "https://api.encore.moe/resource/Data/Game/Aki/UI/UIResources/Common/Image/IconMonsterHead/T_IconMonsterHead_972_UI.png",
                "elements": [
                  {
                    "id": 0,
                    "name": "กายภาพ",
                    "icon": "https://api.encore.moe/resource/Data/Game/Aki/UI/UIResources/Common/Image/IconElement/T_IconElementZero2.png"
                  }
                ]
              },
              {
                "id": 310000310,
                "name": "พลปืนใหญ่แฟรกต์ซิดัส",
                "rarity": {
                  "id": 1,
                  "desc": "ระดับมาตรฐาน (ขุมพลัง 1)"
                },
                "icon": "https://api.encore.moe/resource/Data/Game/Aki/UI/UIResources/Common/Image/IconMonsterHead/T_IconMonsterHead_974_UI.png",
                "elements": [
                  {
                    "id": 0,
                    "name": "กายภาพ",
                    "icon": "https://api.encore.moe/resource/Data/Game/Aki/UI/UIResources/Common/Image/IconElement/T_IconElementZero2.png"
                  }
                ]
              },
              {
                "id": 310000320,
                "name": "พลยิงแฟรกต์ซิดัส",
                "rarity": {
                  "id": 1,
                  "desc": "ระดับมาตรฐาน (ขุมพลัง 1)"
                },
                "icon": "https://api.encore.moe/resource/Data/Game/Aki/UI/UIResources/Common/Image/IconMonsterHead/T_IconMonsterHead_973_UI.png",
                "elements": [
                  {
                    "id": 0,
                    "name": "กายภาพ",
                    "icon": "https://api.encore.moe/resource/Data/Game/Aki/UI/UIResources/Common/Image/IconElement/T_IconElementZero2.png"
                  }
                ]
              },
              {
                "id": 320000200,
                "name": "โครงสร้างสะเก็ดแสง",
                "rarity": {
                  "id": 2,
                  "desc": "ระดับอีลีท (ขุมพลัง 3)"
                },
                "icon": "https://api.encore.moe/resource/Data/Game/Aki/UI/UIResources/Common/Image/IconMonsterHead/T_IconMonsterHead_329_UI.png",
                "elements": [
                  {
                    "id": 1,
                    "name": "กลาซิโอ",
                    "icon": "https://api.encore.moe/resource/Data/Game/Aki/UI/UIResources/Common/Image/IconElement/T_IconElementIce2.png"
                  }
                ]
              }
            ],
            "buffs": [
              {
                "id": 92007114,
                "name": "",
                "desc": "<span style=\"color:#f8e56cff;\">ความต้านทานดาเมจสเปกโตร</span>ของศัตรูลดลง 10%",
                "icon": "https://api.encore.moe/resource/Data/Game/Aki/UI/UIResources/Common/Image/IconAttribute/T_Iconpropertyredattack_UI.png"
              },
              {
                "id": 92008034,
                "name": "",
                "desc": "เมื่อเรโซเนเตอร์ให้การรักษาสมาชิกในทีม การฟื้นฟูพลังงานของเขาจะเพิ่มขึ้น 20% ระยะเวลา 4 วินาที เมื่อเรโซเนเตอร์ได้รับการรักษา Crit. DMG ของเขาจะเพิ่มขึ้น 30% ระยะเวลา 4 วินาที การทริกเกอร์เอฟเฟกต์ซ้ำจะรีเซ็ตระยะเวลาของเอฟเฟกต์",
                "icon": "https://api.encore.moe/resource/Data/Game/Aki/UI/UIResources/Common/Image/IconAttribute/T_Iconpropertyredattack_UI.png"
              }
            ],
            "targets": [
              {
                "id": 1,
                "score": 0,
                "desc": "ผ่านการท้าทาย",
                "rawDesc": "ผ่านการท้าทาย",
                "params": [
                  0
                ]
              },
              {
                "id": 6,
                "score": 120,
                "desc": "ผ่านการท้าทายในเวลาเหลืออย่างน้อย <span style=\"color:#ffd12f;font-weight:bold\">120</span> วินาที",
                "rawDesc": "ผ่านการท้าทายในเวลาเหลืออย่างน้อย {0} วินาที",
                "params": [
                  120
                ]
              },
              {
                "id": 7,
                "score": 180,
                "desc": "ผ่านการท้าทายในเวลาเหลืออย่างน้อย <span style=\"color:#ffd12f;font-weight:bold\">180</span> วินาที",
                "rawDesc": "ผ่านการท้าทายในเวลาเหลืออย่างน้อย {0} วินาที",
                "params": [
                  180
                ]
              }
            ],
            "bgPath": "https://api.encore.moe/resource/Data/Game/Aki/UI/UIResources/UiDailyTower/Image/T_loopTowerBg03_UI_png.png",
            "itemBgPath": "https://api.encore.moe/resource/Data/Game/Aki/UI/UIResources/UiDailyTower/Image/T_DailyTowerL3.png"
          }
        ]
      },
      "4": {
        "4": [
          {
            "id": 182,
            "instanceId": 20016,
            "season": 17,
            "areaNum": 1,
            "floor": 4,
            "cost": 4,
            "difficulty": 3,
            "areaName": "หอคอยเรโซแนนซ์",
            "monsters": [
              {
                "id": 310000370,
                "name": "Galescourge Stalker",
                "rarity": {
                  "id": 1,
                  "desc": "ระดับมาตรฐาน (ขุมพลัง 1)"
                },
                "icon": "https://api.encore.moe/resource/Data/Game/Aki/UI/UIResources/Common/Image/IconMonsterHead/T_IconMonsterHead_31037_UI.png",
                "elements": [
                  {
                    "id": 4,
                    "name": "แอโร",
                    "icon": "https://api.encore.moe/resource/Data/Game/Aki/UI/UIResources/Common/Image/IconElement/T_IconElementWind2.png"
                  }
                ]
              },
              {
                "id": 310000380,
                "name": "Voltscourge Stalker",
                "rarity": {
                  "id": 1,
                  "desc": "ระดับมาตรฐาน (ขุมพลัง 1)"
                },
                "icon": "https://api.encore.moe/resource/Data/Game/Aki/UI/UIResources/Common/Image/IconMonsterHead/T_IconMonsterHead_31038_UI.png",
                "elements": [
                  {
                    "id": 3,
                    "name": "อิเล็กโทร",
                    "icon": "https://api.encore.moe/resource/Data/Game/Aki/UI/UIResources/Common/Image/IconElement/T_IconElementThunder2.png"
                  }
                ]
              },
              {
                "id": 310000390,
                "name": "Frostscourge Stalker",
                "rarity": {
                  "id": 1,
                  "desc": "ระดับมาตรฐาน (ขุมพลัง 1)"
                },
                "icon": "https://api.encore.moe/resource/Data/Game/Aki/UI/UIResources/Common/Image/IconMonsterHead/T_IconMonsterHead_31039_UI.png",
                "elements": [
                  {
                    "id": 1,
                    "name": "กลาซิโอ",
                    "icon": "https://api.encore.moe/resource/Data/Game/Aki/UI/UIResources/Common/Image/IconElement/T_IconElementIce2.png"
                  }
                ]
              },
              {
                "id": 330000030,
                "name": "นกกระยางแห่งความไม่จีรัง",
                "rarity": {
                  "id": 3,
                  "desc": "ระดับโอเวอร์ลอร์ด (ขุมพลัง 4)"
                },
                "icon": "https://api.encore.moe/resource/Data/Game/Aki/UI/UIResources/Common/Image/IconMonsterHead/T_IconMonsterHead_995_UI.png",
                "elements": [
                  {
                    "id": 6,
                    "name": "ฮาว็อค",
                    "icon": "https://api.encore.moe/resource/Data/Game/Aki/UI/UIResources/Common/Image/IconElement/T_IconElementDark2.png"
                  }
                ]
              }
            ],
            "buffs": [
              {
                "id": 92007114,
                "name": "",
                "desc": "<span style=\"color:#f8e56cff;\">ความต้านทานดาเมจสเปกโตร</span>ของศัตรูลดลง 10%",
                "icon": "https://api.encore.moe/resource/Data/Game/Aki/UI/UIResources/Common/Image/IconAttribute/T_Iconpropertyredattack_UI.png"
              },
              {
                "id": 92008034,
                "name": "",
                "desc": "เมื่อเรโซเนเตอร์ให้การรักษาสมาชิกในทีม การฟื้นฟูพลังงานของเขาจะเพิ่มขึ้น 20% ระยะเวลา 4 วินาที เมื่อเรโซเนเตอร์ได้รับการรักษา Crit. DMG ของเขาจะเพิ่มขึ้น 30% ระยะเวลา 4 วินาที การทริกเกอร์เอฟเฟกต์ซ้ำจะรีเซ็ตระยะเวลาของเอฟเฟกต์",
                "icon": "https://api.encore.moe/resource/Data/Game/Aki/UI/UIResources/Common/Image/IconAttribute/T_Iconpropertyredattack_UI.png"
              }
            ],
            "targets": [
              {
                "id": 1,
                "score": 0,
                "desc": "ผ่านการท้าทาย",
                "rawDesc": "ผ่านการท้าทาย",
                "params": [
                  0
                ]
              },
              {
                "id": 6,
                "score": 120,
                "desc": "ผ่านการท้าทายในเวลาเหลืออย่างน้อย <span style=\"color:#ffd12f;font-weight:bold\">120</span> วินาที",
                "rawDesc": "ผ่านการท้าทายในเวลาเหลืออย่างน้อย {0} วินาที",
                "params": [
                  120
                ]
              },
              {
                "id": 7,
                "score": 180,
                "desc": "ผ่านการท้าทายในเวลาเหลืออย่างน้อย <span style=\"color:#ffd12f;font-weight:bold\">180</span> วินาที",
                "rawDesc": "ผ่านการท้าทายในเวลาเหลืออย่างน้อย {0} วินาที",
                "params": [
                  180
                ]
              }
            ],
            "bgPath": "https://api.encore.moe/resource/Data/Game/Aki/UI/UIResources/UiDailyTower/Image/T_loopTowerBg04_UI_png.png",
            "itemBgPath": "https://api.encore.moe/resource/Data/Game/Aki/UI/UIResources/UiDailyTower/Image/T_DailyTowerL4.png"
          }
        ]
      }
    },
    "2": {
      "1": {
        "5": [
          {
            "id": 183,
            "instanceId": 20019,
            "season": 17,
            "areaNum": 2,
            "floor": 1,
            "cost": 5,
            "difficulty": 3,
            "areaName": "หอคอยอันตราย",
            "monsters": [
              {
                "id": 340000010,
                "name": "ราชันไร้มงกุฎ",
                "rarity": {
                  "id": 3,
                  "desc": "ระดับโอเวอร์ลอร์ด (ขุมพลัง 4)"
                },
                "icon": "https://api.encore.moe/resource/Data/Game/Aki/UI/UIResources/Common/Image/IconMonsterHead/T_IconMonsterHead_999_UI.png",
                "elements": [
                  {
                    "id": 6,
                    "name": "ฮาว็อค",
                    "icon": "https://api.encore.moe/resource/Data/Game/Aki/UI/UIResources/Common/Image/IconElement/T_IconElementDark2.png"
                  }
                ]
              }
            ],
            "buffs": [
              {
                "id": 92007130,
                "name": "",
                "desc": "<span style=\"color:#a2fbfc;\">ความต้านทานดาเมจกลาซิโอ</span>และ<span style=\"color:#c7ffed\";>ความต้านทานดาเมจแอโร</span>ของศัตรูลดลง 10% และ<span style=\"color:#ebb0ff;\">ความต้านทานดาเมจอิเล็กโทร</span>และ<span style=\"color:#fcc4db;\">ความต้านทานดาเมจฮาวอก</span>ของศัตรูเพิ่มขึ้น 10%",
                "icon": "https://api.encore.moe/resource/Data/Game/Aki/UI/UIResources/Common/Image/IconAttribute/T_Iconpropertyredattack_UI.png"
              },
              {
                "id": 92008058,
                "name": "",
                "desc": "เมื่อโจมตีประสานโดนเป้าหมาย ATK ของสมาชิกทีมทั้งหมดจะเพิ่มขึ้น 2% และได้รับโบนัส DMG สกิลเรโซแนนซ์ 4% ระยะเวลา 3 วินาที ซ้อนทับได้สูงสุด 10 ชั้นและสูญเสีย 1 ชั้นทุก 3 วินาที การเกิดเอฟเฟกต์ซ้ำจะรีเซ็ตระยะเวลาของเอฟเฟกต์",
                "icon": "https://api.encore.moe/resource/Data/Game/Aki/UI/UIResources/Common/Image/IconAttribute/T_Iconpropertyredattack_UI.png"
              }
            ],
            "targets": [
              {
                "id": 2,
                "score": 90,
                "desc": "ผ่านการท้าทายในเวลาเหลืออย่างน้อย <span style=\"color:#ffd12f;font-weight:bold\">90</span> วินาที",
                "rawDesc": "ผ่านการท้าทายในเวลาเหลืออย่างน้อย {0} วินาที",
                "params": [
                  90
                ]
              },
              {
                "id": 3,
                "score": 150,
                "desc": "ผ่านการท้าทายในเวลาเหลืออย่างน้อย <span style=\"color:#ffd12f;font-weight:bold\">150</span> วินาที",
                "rawDesc": "ผ่านการท้าทายในเวลาเหลืออย่างน้อย {0} วินาที",
                "params": [
                  150
                ]
              },
              {
                "id": 7,
                "score": 180,
                "desc": "ผ่านการท้าทายในเวลาเหลืออย่างน้อย <span style=\"color:#ffd12f;font-weight:bold\">180</span> วินาที",
                "rawDesc": "ผ่านการท้าทายในเวลาเหลืออย่างน้อย {0} วินาที",
                "params": [
                  180
                ]
              }
            ],
            "bgPath": "https://api.encore.moe/resource/Data/Game/Aki/UI/UIResources/UiDailyTower/Image/T_loopTowerBg03_UI_png.png",
            "itemBgPath": "https://api.encore.moe/resource/Data/Game/Aki/UI/UIResources/UiDailyTower/Image/T_DailyTowerL3.png"
          }
        ]
      },
      "2": {
        "5": [
          {
            "id": 184,
            "instanceId": 20020,
            "season": 17,
            "areaNum": 2,
            "floor": 2,
            "cost": 5,
            "difficulty": 3,
            "areaName": "หอคอยอันตราย",
            "monsters": [
              {
                "id": 320000290,
                "name": "Vitreum Dancer",
                "rarity": {
                  "id": 2,
                  "desc": "ระดับอีลีท (ขุมพลัง 3)"
                },
                "icon": "https://api.encore.moe/resource/Data/Game/Aki/UI/UIResources/Common/Image/IconMonsterHead/T_IconMonsterHead_32029_UI.png",
                "elements": [
                  {
                    "id": 3,
                    "name": "อิเล็กโทร",
                    "icon": "https://api.encore.moe/resource/Data/Game/Aki/UI/UIResources/Common/Image/IconElement/T_IconElementThunder2.png"
                  }
                ]
              },
              {
                "id": 320000220,
                "name": "Questless Knight",
                "rarity": {
                  "id": 2,
                  "desc": "ระดับอีลีท (ขุมพลัง 3)"
                },
                "icon": "https://api.encore.moe/resource/Data/Game/Aki/UI/UIResources/Common/Image/IconMonsterHead/T_IconMonsterHead_32022_UI.png",
                "elements": [
                  {
                    "id": 3,
                    "name": "อิเล็กโทร",
                    "icon": "https://api.encore.moe/resource/Data/Game/Aki/UI/UIResources/Common/Image/IconElement/T_IconElementThunder2.png"
                  }
                ]
              },
              {
                "id": 330000010,
                "name": "เมฟิสพายุ",
                "rarity": {
                  "id": 3,
                  "desc": "ระดับโอเวอร์ลอร์ด (ขุมพลัง 4)"
                },
                "icon": "https://api.encore.moe/resource/Data/Game/Aki/UI/UIResources/Common/Image/IconMonsterHead/T_IconMonsterHead_225_UI.png",
                "elements": [
                  {
                    "id": 3,
                    "name": "อิเล็กโทร",
                    "icon": "https://api.encore.moe/resource/Data/Game/Aki/UI/UIResources/Common/Image/IconElement/T_IconElementThunder2.png"
                  }
                ]
              }
            ],
            "buffs": [
              {
                "id": 92007130,
                "name": "",
                "desc": "<span style=\"color:#a2fbfc;\">ความต้านทานดาเมจกลาซิโอ</span>และ<span style=\"color:#c7ffed\";>ความต้านทานดาเมจแอโร</span>ของศัตรูลดลง 10% และ<span style=\"color:#ebb0ff;\">ความต้านทานดาเมจอิเล็กโทร</span>และ<span style=\"color:#fcc4db;\">ความต้านทานดาเมจฮาวอก</span>ของศัตรูเพิ่มขึ้น 10%",
                "icon": "https://api.encore.moe/resource/Data/Game/Aki/UI/UIResources/Common/Image/IconAttribute/T_Iconpropertyredattack_UI.png"
              },
              {
                "id": 92008058,
                "name": "",
                "desc": "เมื่อโจมตีประสานโดนเป้าหมาย ATK ของสมาชิกทีมทั้งหมดจะเพิ่มขึ้น 2% และได้รับโบนัส DMG สกิลเรโซแนนซ์ 4% ระยะเวลา 3 วินาที ซ้อนทับได้สูงสุด 10 ชั้นและสูญเสีย 1 ชั้นทุก 3 วินาที การเกิดเอฟเฟกต์ซ้ำจะรีเซ็ตระยะเวลาของเอฟเฟกต์",
                "icon": "https://api.encore.moe/resource/Data/Game/Aki/UI/UIResources/Common/Image/IconAttribute/T_Iconpropertyredattack_UI.png"
              }
            ],
            "targets": [
              {
                "id": 2,
                "score": 90,
                "desc": "ผ่านการท้าทายในเวลาเหลืออย่างน้อย <span style=\"color:#ffd12f;font-weight:bold\">90</span> วินาที",
                "rawDesc": "ผ่านการท้าทายในเวลาเหลืออย่างน้อย {0} วินาที",
                "params": [
                  90
                ]
              },
              {
                "id": 3,
                "score": 150,
                "desc": "ผ่านการท้าทายในเวลาเหลืออย่างน้อย <span style=\"color:#ffd12f;font-weight:bold\">150</span> วินาที",
                "rawDesc": "ผ่านการท้าทายในเวลาเหลืออย่างน้อย {0} วินาที",
                "params": [
                  150
                ]
              },
              {
                "id": 7,
                "score": 180,
                "desc": "ผ่านการท้าทายในเวลาเหลืออย่างน้อย <span style=\"color:#ffd12f;font-weight:bold\">180</span> วินาที",
                "rawDesc": "ผ่านการท้าทายในเวลาเหลืออย่างน้อย {0} วินาที",
                "params": [
                  180
                ]
              }
            ],
            "bgPath": "https://api.encore.moe/resource/Data/Game/Aki/UI/UIResources/UiDailyTower/Image/T_loopTowerBg04_UI_png.png",
            "itemBgPath": "https://api.encore.moe/resource/Data/Game/Aki/UI/UIResources/UiDailyTower/Image/T_DailyTowerL4.png"
          }
        ]
      }
    },
    "3": {
      "1": {
        "1": [
          {
            "id": 185,
            "instanceId": 20021,
            "season": 17,
            "areaNum": 3,
            "floor": 1,
            "cost": 1,
            "difficulty": 3,
            "areaName": "หอคอยสะท้อนเสียง",
            "monsters": [
              {
                "id": 320000130,
                "name": "เคียวคมกริบ",
                "rarity": {
                  "id": 2,
                  "desc": "ระดับอีลีท (ขุมพลัง 3)"
                },
                "icon": "https://api.encore.moe/resource/Data/Game/Aki/UI/UIResources/Common/Image/IconMonsterHead/T_IconMonsterHead_970_UI.png",
                "elements": [
                  {
                    "id": 4,
                    "name": "แอโร",
                    "icon": "https://api.encore.moe/resource/Data/Game/Aki/UI/UIResources/Common/Image/IconElement/T_IconElementWind2.png"
                  }
                ]
              },
              {
                "id": 310000330,
                "name": "โคมไฟจราจร",
                "rarity": {
                  "id": 1,
                  "desc": "ระดับมาตรฐาน (ขุมพลัง 1)"
                },
                "icon": "https://api.encore.moe/resource/Data/Game/Aki/UI/UIResources/Common/Image/IconMonsterHead/T_IconMonsterHead_1000_UI.png",
                "elements": [
                  {
                    "id": 5,
                    "name": "สเปกโตร",
                    "icon": "https://api.encore.moe/resource/Data/Game/Aki/UI/UIResources/Common/Image/IconElement/T_IconElementLight2.png"
                  }
                ]
              }
            ],
            "buffs": [
              {
                "id": 92007110,
                "name": "",
                "desc": "<span style=\"color:#a2fbfc;\">ความต้านทานดาเมจกลาซิโอ</span>ของศัตรูลดลง 10%",
                "icon": "https://api.encore.moe/resource/Data/Game/Aki/UI/UIResources/Common/Image/IconAttribute/T_Iconpropertyredattack_UI.png"
              },
              {
                "id": 92008055,
                "name": "",
                "desc": "เมื่อเรโซเนเตอร์ใช้การปลดปล่อยเรโซแนนซ์ ATK จะเพิ่มขึ้น 5% และได้รับโบนัส DMG สกิลเรโซแนนซ์ 10% เป็นเวลา 3 วินาที ซ้อนทับได้สูงสุด 4 ชั้น เอฟเฟกต์จะถูกยกเลิกเมื่อสลับตัวเรโซเนเตอร์ที่ใช้งานอยู่ออกจากสนาม",
                "icon": "https://api.encore.moe/resource/Data/Game/Aki/UI/UIResources/Common/Image/IconAttribute/T_Iconpropertyredattack_UI.png"
              }
            ],
            "targets": [
              {
                "id": 1,
                "score": 0,
                "desc": "ผ่านการท้าทาย",
                "rawDesc": "ผ่านการท้าทาย",
                "params": [
                  0
                ]
              },
              {
                "id": 2,
                "score": 90,
                "desc": "ผ่านการท้าทายในเวลาเหลืออย่างน้อย <span style=\"color:#ffd12f;font-weight:bold\">90</span> วินาที",
                "rawDesc": "ผ่านการท้าทายในเวลาเหลืออย่างน้อย {0} วินาที",
                "params": [
                  90
                ]
              },
              {
                "id": 3,
                "score": 150,
                "desc": "ผ่านการท้าทายในเวลาเหลืออย่างน้อย <span style=\"color:#ffd12f;font-weight:bold\">150</span> วินาที",
                "rawDesc": "ผ่านการท้าทายในเวลาเหลืออย่างน้อย {0} วินาที",
                "params": [
                  150
                ]
              }
            ],
            "bgPath": "https://api.encore.moe/resource/Data/Game/Aki/UI/UIResources/UiDailyTower/Image/T_loopTowerBg01_UI_png.png",
            "itemBgPath": "https://api.encore.moe/resource/Data/Game/Aki/UI/UIResources/UiDailyTower/Image/T_DailyTowerL1.png"
          }
        ]
      },
      "2": {
        "2": [
          {
            "id": 186,
            "instanceId": 20022,
            "season": 17,
            "areaNum": 3,
            "floor": 2,
            "cost": 2,
            "difficulty": 3,
            "areaName": "หอคอยสะท้อนเสียง",
            "monsters": [
              {
                "id": 310000280,
                "name": "Fusion Dreadmane",
                "rarity": {
                  "id": 1,
                  "desc": "ระดับมาตรฐาน (ขุมพลัง 1)"
                },
                "icon": "https://api.encore.moe/resource/Data/Game/Aki/UI/UIResources/Common/Image/IconMonsterHead/T_IconMonsterHead_980_UI.png",
                "elements": [
                  {
                    "id": 2,
                    "name": "ฟิวชัน",
                    "icon": "https://api.encore.moe/resource/Data/Game/Aki/UI/UIResources/Common/Image/IconElement/T_IconElementFire2.png"
                  }
                ]
              },
              {
                "id": 310000350,
                "name": "Lava Larva",
                "rarity": {
                  "id": 1,
                  "desc": "ระดับมาตรฐาน (ขุมพลัง 1)"
                },
                "icon": "https://api.encore.moe/resource/Data/Game/Aki/UI/UIResources/Common/Image/IconMonsterHead/T_IconMonsterHead_326_UI.png",
                "elements": [
                  {
                    "id": 2,
                    "name": "ฟิวชัน",
                    "icon": "https://api.encore.moe/resource/Data/Game/Aki/UI/UIResources/Common/Image/IconElement/T_IconElementFire2.png"
                  }
                ]
              }
            ],
            "buffs": [
              {
                "id": 92007110,
                "name": "",
                "desc": "<span style=\"color:#a2fbfc;\">ความต้านทานดาเมจกลาซิโอ</span>ของศัตรูลดลง 10%",
                "icon": "https://api.encore.moe/resource/Data/Game/Aki/UI/UIResources/Common/Image/IconAttribute/T_Iconpropertyredattack_UI.png"
              },
              {
                "id": 92008055,
                "name": "",
                "desc": "เมื่อเรโซเนเตอร์ใช้การปลดปล่อยเรโซแนนซ์ ATK จะเพิ่มขึ้น 5% และได้รับโบนัส DMG สกิลเรโซแนนซ์ 10% เป็นเวลา 3 วินาที ซ้อนทับได้สูงสุด 4 ชั้น เอฟเฟกต์จะถูกยกเลิกเมื่อสลับตัวเรโซเนเตอร์ที่ใช้งานอยู่ออกจากสนาม",
                "icon": "https://api.encore.moe/resource/Data/Game/Aki/UI/UIResources/Common/Image/IconAttribute/T_Iconpropertyredattack_UI.png"
              }
            ],
            "targets": [
              {
                "id": 1,
                "score": 0,
                "desc": "ผ่านการท้าทาย",
                "rawDesc": "ผ่านการท้าทาย",
                "params": [
                  0
                ]
              },
              {
                "id": 2,
                "score": 90,
                "desc": "ผ่านการท้าทายในเวลาเหลืออย่างน้อย <span style=\"color:#ffd12f;font-weight:bold\">90</span> วินาที",
                "rawDesc": "ผ่านการท้าทายในเวลาเหลืออย่างน้อย {0} วินาที",
                "params": [
                  90
                ]
              },
              {
                "id": 3,
                "score": 150,
                "desc": "ผ่านการท้าทายในเวลาเหลืออย่างน้อย <span style=\"color:#ffd12f;font-weight:bold\">150</span> วินาที",
                "rawDesc": "ผ่านการท้าทายในเวลาเหลืออย่างน้อย {0} วินาที",
                "params": [
                  150
                ]
              }
            ],
            "bgPath": "https://api.encore.moe/resource/Data/Game/Aki/UI/UIResources/UiDailyTower/Image/T_loopTowerBg02_UI_png.png",
            "itemBgPath": "https://api.encore.moe/resource/Data/Game/Aki/UI/UIResources/UiDailyTower/Image/T_DailyTowerL2.png"
          }
        ]
      },
      "3": {
        "3": [
          {
            "id": 187,
            "instanceId": 20023,
            "season": 17,
            "areaNum": 3,
            "floor": 3,
            "cost": 3,
            "difficulty": 3,
            "areaName": "หอคอยสะท้อนเสียง",
            "monsters": [
              {
                "id": 320000230,
                "name": "Diurnus Knight",
                "rarity": {
                  "id": 2,
                  "desc": "ระดับอีลีท (ขุมพลัง 3)"
                },
                "icon": "https://api.encore.moe/resource/Data/Game/Aki/UI/UIResources/Common/Image/IconMonsterHead/T_IconMonsterHead_32023_UI.png",
                "elements": [
                  {
                    "id": 5,
                    "name": "สเปกโตร",
                    "icon": "https://api.encore.moe/resource/Data/Game/Aki/UI/UIResources/Common/Image/IconElement/T_IconElementLight2.png"
                  }
                ]
              }
            ],
            "buffs": [
              {
                "id": 92007110,
                "name": "",
                "desc": "<span style=\"color:#a2fbfc;\">ความต้านทานดาเมจกลาซิโอ</span>ของศัตรูลดลง 10%",
                "icon": "https://api.encore.moe/resource/Data/Game/Aki/UI/UIResources/Common/Image/IconAttribute/T_Iconpropertyredattack_UI.png"
              },
              {
                "id": 92008055,
                "name": "",
                "desc": "เมื่อเรโซเนเตอร์ใช้การปลดปล่อยเรโซแนนซ์ ATK จะเพิ่มขึ้น 5% และได้รับโบนัส DMG สกิลเรโซแนนซ์ 10% เป็นเวลา 3 วินาที ซ้อนทับได้สูงสุด 4 ชั้น เอฟเฟกต์จะถูกยกเลิกเมื่อสลับตัวเรโซเนเตอร์ที่ใช้งานอยู่ออกจากสนาม",
                "icon": "https://api.encore.moe/resource/Data/Game/Aki/UI/UIResources/Common/Image/IconAttribute/T_Iconpropertyredattack_UI.png"
              }
            ],
            "targets": [
              {
                "id": 1,
                "score": 0,
                "desc": "ผ่านการท้าทาย",
                "rawDesc": "ผ่านการท้าทาย",
                "params": [
                  0
                ]
              },
              {
                "id": 6,
                "score": 120,
                "desc": "ผ่านการท้าทายในเวลาเหลืออย่างน้อย <span style=\"color:#ffd12f;font-weight:bold\">120</span> วินาที",
                "rawDesc": "ผ่านการท้าทายในเวลาเหลืออย่างน้อย {0} วินาที",
                "params": [
                  120
                ]
              },
              {
                "id": 7,
                "score": 180,
                "desc": "ผ่านการท้าทายในเวลาเหลืออย่างน้อย <span style=\"color:#ffd12f;font-weight:bold\">180</span> วินาที",
                "rawDesc": "ผ่านการท้าทายในเวลาเหลืออย่างน้อย {0} วินาที",
                "params": [
                  180
                ]
              }
            ],
            "bgPath": "https://api.encore.moe/resource/Data/Game/Aki/UI/UIResources/UiDailyTower/Image/T_loopTowerBg03_UI_png.png",
            "itemBgPath": "https://api.encore.moe/resource/Data/Game/Aki/UI/UIResources/UiDailyTower/Image/T_DailyTowerL3.png"
          }
        ]
      },
      "4": {
        "4": [
          {
            "id": 188,
            "instanceId": 20024,
            "season": 17,
            "areaNum": 3,
            "floor": 4,
            "cost": 4,
            "difficulty": 3,
            "areaName": "หอคอยสะท้อนเสียง",
            "monsters": [
              {
                "id": 330000060,
                "name": "ปักษาครวญ",
                "rarity": {
                  "id": 3,
                  "desc": "ระดับโอเวอร์ลอร์ด (ขุมพลัง 4)"
                },
                "icon": "https://api.encore.moe/resource/Data/Game/Aki/UI/UIResources/Common/Image/IconMonsterHead/T_IconMonsterHead_997_UI.png",
                "elements": [
                  {
                    "id": 5,
                    "name": "สเปกโตร",
                    "icon": "https://api.encore.moe/resource/Data/Game/Aki/UI/UIResources/Common/Image/IconElement/T_IconElementLight2.png"
                  }
                ]
              }
            ],
            "buffs": [
              {
                "id": 92007110,
                "name": "",
                "desc": "<span style=\"color:#a2fbfc;\">ความต้านทานดาเมจกลาซิโอ</span>ของศัตรูลดลง 10%",
                "icon": "https://api.encore.moe/resource/Data/Game/Aki/UI/UIResources/Common/Image/IconAttribute/T_Iconpropertyredattack_UI.png"
              },
              {
                "id": 92008055,
                "name": "",
                "desc": "เมื่อเรโซเนเตอร์ใช้การปลดปล่อยเรโซแนนซ์ ATK จะเพิ่มขึ้น 5% และได้รับโบนัส DMG สกิลเรโซแนนซ์ 10% เป็นเวลา 3 วินาที ซ้อนทับได้สูงสุด 4 ชั้น เอฟเฟกต์จะถูกยกเลิกเมื่อสลับตัวเรโซเนเตอร์ที่ใช้งานอยู่ออกจากสนาม",
                "icon": "https://api.encore.moe/resource/Data/Game/Aki/UI/UIResources/Common/Image/IconAttribute/T_Iconpropertyredattack_UI.png"
              }
            ],
            "targets": [
              {
                "id": 1,
                "score": 0,
                "desc": "ผ่านการท้าทาย",
                "rawDesc": "ผ่านการท้าทาย",
                "params": [
                  0
                ]
              },
              {
                "id": 6,
                "score": 120,
                "desc": "ผ่านการท้าทายในเวลาเหลืออย่างน้อย <span style=\"color:#ffd12f;font-weight:bold\">120</span> วินาที",
                "rawDesc": "ผ่านการท้าทายในเวลาเหลืออย่างน้อย {0} วินาที",
                "params": [
                  120
                ]
              },
              {
                "id": 7,
                "score": 180,
                "desc": "ผ่านการท้าทายในเวลาเหลืออย่างน้อย <span style=\"color:#ffd12f;font-weight:bold\">180</span> วินาที",
                "rawDesc": "ผ่านการท้าทายในเวลาเหลืออย่างน้อย {0} วินาที",
                "params": [
                  180
                ]
              }
            ],
            "bgPath": "https://api.encore.moe/resource/Data/Game/Aki/UI/UIResources/UiDailyTower/Image/T_loopTowerBg04_UI_png.png",
            "itemBgPath": "https://api.encore.moe/resource/Data/Game/Aki/UI/UIResources/UiDailyTower/Image/T_DailyTowerL4.png"
          }
        ]
      }
    }
  }
}